strava_cz/__init__.py
strava_cz/main.py
strava_cz-0.2.0.dist-info/licenses/LICENSE
strava_cz-0.2.0.dist-info/METADATA
strava_cz-0.2.0.dist-info/WHEEL
strava_cz-0.2.0.dist-info/top_level.txt
strava_cz-0.2.0.dist-info/RECORD
