Metadata-Version: 2.4
Name: strava-cz
Version: 0.2.0
Summary: High level API pro interakci s webovou aplikaci Strava.cz
Author-email: Vojtěch Nerad <ja@jsem-nerad.cz>
License-Expression: GPL-3.0-or-later
Project-URL: Homepage, https://github.com/jsem-nerad/strava-cz-python
Project-URL: Documentation, https://github.com/jsem-nerad/strava-cz-python#readme
Project-URL: Repository, https://github.com/jsem-nerad/strava-cz-python
Project-URL: Issues, https://github.com/jsem-nerad/strava-cz-python/issues
Keywords: czech,canteen,food,school,strava,jidelna,api,scraper,web-scraping
Classifier: Development Status :: 4 - Beta
Classifier: Intended Audience :: Developers
Classifier: Programming Language :: Python :: 3
Classifier: Programming Language :: Python :: 3.9
Classifier: Programming Language :: Python :: 3.10
Classifier: Programming Language :: Python :: 3.11
Classifier: Programming Language :: Python :: 3.12
Classifier: Natural Language :: Czech
Classifier: Topic :: Education
Classifier: Topic :: Internet :: WWW/HTTP :: Session
Requires-Python: >=3.9
License-File: LICENSE
Requires-Dist: requests>=2.25.0
Provides-Extra: dev
Requires-Dist: pytest>=7.0.0; extra == "dev"
Requires-Dist: pytest-cov>=4.0.0; extra == "dev"
Requires-Dist: black>=23.0.0; extra == "dev"
Requires-Dist: flake8>=6.0.0; extra == "dev"
Requires-Dist: mypy>=1.0.0; extra == "dev"
Requires-Dist: types-requests>=2.25.0; extra == "dev"
Dynamic: license-file
